z3c.csvvocabulary-3.0-py3.9-nspkg.pth
z3c/csvvocabulary/README.rst
z3c/csvvocabulary/__init__.py
z3c/csvvocabulary/i18nextract.py
z3c/csvvocabulary/tests.py
z3c/csvvocabulary/vocabulary.py
z3c/csvvocabulary/testing/data/sample.csv
z3c/csvvocabulary/testing/data/utf-8.csv
z3c.csvvocabulary-3.0.dist-info/LICENSE.rst
z3c.csvvocabulary-3.0.dist-info/METADATA
z3c.csvvocabulary-3.0.dist-info/WHEEL
z3c.csvvocabulary-3.0.dist-info/namespace_packages.txt
z3c.csvvocabulary-3.0.dist-info/top_level.txt
z3c.csvvocabulary-3.0.dist-info/RECORD
