Metadata-Version: 2.1
Name: z3c.csvvocabulary
Version: 3.0
Summary: A package to create vocabularies based on CSV files.
Home-page: https://https://github.com/zopefoundation/z3c.csvvocabulary
Author: Zope Community
Author-email: zope-dev@zope.dev
License: ZPL 2.1
Keywords: zope3 vocabulary csv
Classifier: Development Status :: 5 - Production/Stable
Classifier: Intended Audience :: Developers
Classifier: License :: OSI Approved :: Zope Public License
Classifier: Natural Language :: English
Classifier: Operating System :: OS Independent
Classifier: Programming Language :: Python
Classifier: Programming Language :: Python :: 3
Classifier: Programming Language :: Python :: 3.7
Classifier: Programming Language :: Python :: 3.8
Classifier: Programming Language :: Python :: 3.9
Classifier: Programming Language :: Python :: 3.10
Classifier: Programming Language :: Python :: 3.11
Classifier: Programming Language :: Python :: Implementation :: CPython
Classifier: Programming Language :: Python :: Implementation :: PyPy
Classifier: Topic :: Internet :: WWW/HTTP
Classifier: Framework :: Zope :: 3
Requires-Python: >=3.7
License-File: LICENSE.rst
Requires-Dist: setuptools
Requires-Dist: zope.i18nmessageid
Requires-Dist: zope.schema
Provides-Extra: test
Requires-Dist: zope.testing ; extra == 'test'
